README.md
setup.py
synapsepy/__init__.py
synapsepy/client.py
synapsepy/endpoints.py
synapsepy/errors.py
synapsepy/http_client.py
synapsepy/node.py
synapsepy/subnet.py
synapsepy/subscription.py
synapsepy/transaction.py
synapsepy/user.py
synapsepy.egg-info/PKG-INFO
synapsepy.egg-info/SOURCES.txt
synapsepy.egg-info/dependency_links.txt
synapsepy.egg-info/requires.txt
synapsepy.egg-info/top_level.txt