Metadata-Version: 1.1
Name: synapsepy
Version: 1.2.2
Summary: SynapseFi Python Library
Home-page: https://github.com/SynapseFI/SynapseFi-Python-v2
Author: Synapse Financial Technologies Inc.
Author-email: help@synapsefi.com
License: MIT
Keywords: SynapseFi v3 API Wrapper
Platform: UNKNOWN
Classifier: Development Status :: 4 - Beta
Classifier: Intended Audience :: Developers
Classifier: License :: OSI Approved :: MIT License
Classifier: Programming Language :: Python :: 3
